anndata/__init__.py
anndata/_settings.py
anndata/_settings.pyi
anndata/_types.py
anndata/_warnings.py
anndata/abc.py
anndata/io.py
anndata/logging.py
anndata/types.py
anndata/typing.py
anndata/utils.py
anndata/_core/__init__.py
anndata/_core/access.py
anndata/_core/aligned_df.py
anndata/_core/aligned_mapping.py
anndata/_core/anndata.py
anndata/_core/extensions.py
anndata/_core/file_backing.py
anndata/_core/index.py
anndata/_core/merge.py
anndata/_core/raw.py
anndata/_core/sparse_dataset.py
anndata/_core/storage.py
anndata/_core/views.py
anndata/_core/xarray.py
anndata/_io/__init__.py
anndata/_io/h5ad.py
anndata/_io/read.py
anndata/_io/utils.py
anndata/_io/write.py
anndata/_io/zarr.py
anndata/_io/specs/__init__.py
anndata/_io/specs/lazy_methods.py
anndata/_io/specs/methods.py
anndata/_io/specs/registry.py
anndata/compat/__init__.py
anndata/experimental/__init__.py
anndata/experimental/_dispatch_io.py
anndata/experimental/merge.py
anndata/experimental/backed/__init__.py
anndata/experimental/backed/_compat.py
anndata/experimental/backed/_io.py
anndata/experimental/backed/_lazy_arrays.py
anndata/experimental/multi_files/__init__.py
anndata/experimental/multi_files/_anncollection.py
anndata/experimental/pytorch/__init__.py
anndata/experimental/pytorch/_annloader.py
anndata/tests/__init__.py
anndata/tests/helpers.py
testing/anndata/__init__.py
testing/anndata/_doctest.py
testing/anndata/_pytest.py
testing/anndata/py.typed
anndata-0.12.6.dist-info/METADATA
anndata-0.12.6.dist-info/WHEEL
anndata-0.12.6.dist-info/licenses/LICENSE
anndata-0.12.6.dist-info/RECORD
