Metadata-Version: 2.4
Name: anndata
Version: 0.12.6
Summary: Annotated data.
Project-URL: Documentation, https://anndata.readthedocs.io/
Project-URL: Source, https://github.com/scverse/anndata
Project-URL: Home-page, https://github.com/scverse/anndata
Author: Philipp Angerer, Alex Wolf, Isaac Virshup, Sergei Rybakov, Ilan Gold
Maintainer-email: Philipp Angerer <philipp.angerer@helmholtz-munich.de>, Ilan Gold <ilan.gold@helmholtz-munich.de>
License-Expression: BSD-3-Clause
License-File: LICENSE
Classifier: Environment :: Console
Classifier: Framework :: Jupyter
Classifier: Intended Audience :: Developers
Classifier: Intended Audience :: Science/Research
Classifier: Natural Language :: English
Classifier: Operating System :: MacOS :: MacOS X
Classifier: Operating System :: Microsoft :: Windows
Classifier: Operating System :: POSIX :: Linux
Classifier: Programming Language :: Python :: 3
Classifier: Programming Language :: Python :: 3.11
Classifier: Programming Language :: Python :: 3.12
Classifier: Programming Language :: Python :: 3.13
Classifier: Programming Language :: Python :: 3.14
Classifier: Topic :: Scientific/Engineering :: Bio-Informatics
Classifier: Topic :: Scientific/Engineering :: Visualization
Requires-Python: >=3.11
Requires-Dist: array-api-compat>=1.7.1
Requires-Dist: h5py>=3.8
Requires-Dist: legacy-api-wrap
Requires-Dist: natsort
Requires-Dist: numpy>=1.26
Requires-Dist: packaging>=24.2
Requires-Dist: pandas!=2.1.2,>=2.1.0
Requires-Dist: scipy>=1.12
Requires-Dist: zarr!=3.0.*,>=2.18.7
Provides-Extra: cu11
Requires-Dist: cupy-cuda11x; extra == 'cu11'
Provides-Extra: cu12
Requires-Dist: cupy-cuda12x; extra == 'cu12'
Provides-Extra: dask
Requires-Dist: dask[array]!=2024.8.*,!=2024.9.*,!=2025.2.*,!=2025.3.*,!=2025.4.*,!=2025.5.*,!=2025.6.*,!=2025.7.*,!=2025.8.*,>=2023.5.1; extra == 'dask'
Provides-Extra: dev
Requires-Dist: towncrier>=24.8.0; extra == 'dev'
Provides-Extra: dev-doc
Requires-Dist: towncrier>=24.8.0; extra == 'dev-doc'
Provides-Extra: doc
Requires-Dist: awkward>=2.3; extra == 'doc'
Requires-Dist: dask[array]!=2024.8.*,!=2024.9.*,!=2025.2.*,!=2025.3.*,!=2025.4.*,!=2025.5.*,!=2025.6.*,!=2025.7.*,!=2025.8.*,>=2023.5.1; extra == 'doc'
Requires-Dist: ipython; extra == 'doc'
Requires-Dist: myst-nb; extra == 'doc'
Requires-Dist: myst-parser; extra == 'doc'
Requires-Dist: scanpydoc[theme,typehints]>=0.15.3; extra == 'doc'
Requires-Dist: sphinx-autodoc-typehints>=2.2.0; extra == 'doc'
Requires-Dist: sphinx-book-theme>=1.1.0; extra == 'doc'
Requires-Dist: sphinx-copybutton; extra == 'doc'
Requires-Dist: sphinx-design>=0.5.0; extra == 'doc'
Requires-Dist: sphinx-issues>=5.0.1; extra == 'doc'
Requires-Dist: sphinx-toolbox>=3.8.0; extra == 'doc'
Requires-Dist: sphinx>=8.2.1; extra == 'doc'
Requires-Dist: sphinxext-opengraph; extra == 'doc'
Requires-Dist: towncrier>=24.8.0; extra == 'doc'
Provides-Extra: gpu
Requires-Dist: cupy; extra == 'gpu'
Provides-Extra: lazy
Requires-Dist: aiohttp; extra == 'lazy'
Requires-Dist: dask[array]!=2024.8.*,!=2024.9.*,!=2025.2.*,!=2025.3.*,!=2025.4.*,!=2025.5.*,!=2025.6.*,!=2025.7.*,!=2025.8.*,>=2023.5.1; extra == 'lazy'
Requires-Dist: requests; extra == 'lazy'
Requires-Dist: xarray>=2025.06.1; extra == 'lazy'
Provides-Extra: test
Requires-Dist: aiohttp; extra == 'test'
Requires-Dist: awkward>=2.3.2; extra == 'test'
Requires-Dist: boltons; extra == 'test'
Requires-Dist: dask[array]!=2024.8.*,!=2024.9.*,!=2025.2.*,!=2025.3.*,!=2025.4.*,!=2025.5.*,!=2025.6.*,!=2025.7.*,!=2025.8.*,>=2023.5.1; extra == 'test'
Requires-Dist: dask[distributed]; extra == 'test'
Requires-Dist: filelock; extra == 'test'
Requires-Dist: httpx<1.0; extra == 'test'
Requires-Dist: joblib; extra == 'test'
Requires-Dist: loompy>=3.0.5; extra == 'test'
Requires-Dist: matplotlib; extra == 'test'
Requires-Dist: openpyxl; extra == 'test'
Requires-Dist: pyarrow; extra == 'test'
Requires-Dist: pytest-cov; extra == 'test'
Requires-Dist: pytest-memray; extra == 'test'
Requires-Dist: pytest-mock; extra == 'test'
Requires-Dist: pytest-randomly; extra == 'test'
Requires-Dist: pytest-xdist[psutil]; extra == 'test'
Requires-Dist: pytest<8.3.4,>=8.2; extra == 'test'
Requires-Dist: requests; extra == 'test'
Requires-Dist: scanpy>=1.10; extra == 'test'
Requires-Dist: scikit-learn; extra == 'test'
Requires-Dist: xarray>=2025.06.1; extra == 'test'
Provides-Extra: test-min
Requires-Dist: awkward>=2.3.2; extra == 'test-min'
Requires-Dist: boltons; extra == 'test-min'
Requires-Dist: dask[array]!=2024.8.*,!=2024.9.*,!=2025.2.*,!=2025.3.*,!=2025.4.*,!=2025.5.*,!=2025.6.*,!=2025.7.*,!=2025.8.*,>=2023.5.1; extra == 'test-min'
Requires-Dist: dask[distributed]; extra == 'test-min'
Requires-Dist: filelock; extra == 'test-min'
Requires-Dist: httpx<1.0; extra == 'test-min'
Requires-Dist: joblib; extra == 'test-min'
Requires-Dist: loompy>=3.0.5; extra == 'test-min'
Requires-Dist: matplotlib; extra == 'test-min'
Requires-Dist: openpyxl; extra == 'test-min'
Requires-Dist: pyarrow; extra == 'test-min'
Requires-Dist: pytest-cov; extra == 'test-min'
Requires-Dist: pytest-memray; extra == 'test-min'
Requires-Dist: pytest-mock; extra == 'test-min'
Requires-Dist: pytest-randomly; extra == 'test-min'
Requires-Dist: pytest-xdist[psutil]; extra == 'test-min'
Requires-Dist: pytest<8.3.4,>=8.2; extra == 'test-min'
Requires-Dist: scanpy>=1.10; extra == 'test-min'
Requires-Dist: scikit-learn; extra == 'test-min'
